{
  "annotations": {
    "changelogDate": "20241023174759"
  },
  "applications": ["jhmapstruct"],
  "fields": [
    {
      "fieldName": "amount",
      "fieldType": "BigDecimal",
      "fieldValidateRules": ["required"]
    },
    {
      "fieldName": "paymentDate",
      "fieldType": "Instant",
      "fieldValidateRules": ["required"]
    },
    {
      "fieldName": "paymentMethod",
      "fieldType": "NextPaymentMethod",
      "fieldValues": "CREDIT_CARD,PAYPAL,BANK_TRANSFER"
    }
  ],
  "jpaMetamodelFiltering": true,
  "name": "NextPayment",
  "pagination": "pagination",
  "relationships": [
    {
      "options": {
        "onDelete": "CASCADE"
      },
      "otherEntityName": "masterTenant",
      "relationshipName": "tenant",
      "relationshipSide": "left",
      "relationshipType": "many-to-one"
    }
  ],
  "searchEngine": "no",
  "service": "serviceClass"
}
